docs/conf.py
helium/__init__.py
helium/_impl/__init__.py
helium/_impl/match_type.py
helium/_impl/selenium_wrappers.py
helium/_impl/util/__init__.py
helium/_impl/util/dictionary.py
helium/_impl/util/geom.py
helium/_impl/util/html.py
helium/_impl/util/inspect_.py
helium/_impl/util/lang.py
helium/_impl/util/path.py
helium/_impl/util/system.py
helium/_impl/util/xpath.py
qsobad_helium-5.1.0.dist-info/LICENSE.txt
qsobad_helium-5.1.0.dist-info/METADATA
qsobad_helium-5.1.0.dist-info/NOTICE.txt
qsobad_helium-5.1.0.dist-info/WHEEL
qsobad_helium-5.1.0.dist-info/top_level.txt
qsobad_helium-5.1.0.dist-info/RECORD
