Metadata-Version: 2.2
Name: qsobad_helium
Version: 5.1.0
Summary: Lighter browser automation based on Selenium.
Home-page: https://github.com/mherrmann/helium
Author: Michael Herrmann
Author-email: Michael Herrmann <michael+removethisifyouarehuman@herrmann.io>
License: MIT
Keywords: helium,selenium,browser,automation
Classifier: Development Status :: 5 - Production/Stable
Classifier: Intended Audience :: Developers
Classifier: License :: OSI Approved :: MIT License
Classifier: Topic :: Software Development :: Testing
Classifier: Topic :: Software Development :: Libraries
Classifier: Programming Language :: Python :: 3
Classifier: Operating System :: Microsoft :: Windows
Classifier: Operating System :: POSIX :: Linux
Classifier: Operating System :: MacOS :: MacOS X
Requires-Python: >=3
License-File: LICENSE.txt
License-File: NOTICE.txt
Requires-Dist: selenium>=4.16.0
Dynamic: author
Dynamic: home-page
Dynamic: requires-python
